streamlit_sortables/__init__.py
streamlit_sortables/frontend/build/asset-manifest.json
streamlit_sortables/frontend/build/bootstrap.min.css
streamlit_sortables/frontend/build/bootstrap.min.css.map
streamlit_sortables/frontend/build/index.html
streamlit_sortables/frontend/build/static/css/main.be46d1d7.css
streamlit_sortables/frontend/build/static/css/main.be46d1d7.css.map
streamlit_sortables/frontend/build/static/js/main.90335706.js
streamlit_sortables/frontend/build/static/js/main.90335706.js.LICENSE.txt
streamlit_sortables/frontend/build/static/js/main.90335706.js.map
streamlit_sortables-0.3.0.dist-info/LICENSE
streamlit_sortables-0.3.0.dist-info/METADATA
streamlit_sortables-0.3.0.dist-info/WHEEL
streamlit_sortables-0.3.0.dist-info/RECORD
