Metadata-Version: 2.1
Name: streamlit-sortables
Version: 0.3.0
Summary: A Streamlit component to provide sortable list.
Home-page: https://github.com/ohtaman/streamlit-sortables
License: MIT
Keywords: streamlit,sortable,list
Author: ohtaman
Author-email: ohtamans@gmail.com
Requires-Python: >=3.9, !=2.7.*, !=3.0.*, !=3.1.*, !=3.2.*, !=3.3.*, !=3.4.*, !=3.5.*, !=3.6.*, !=3.7.*, !=3.8.*
Classifier: Development Status :: 3 - Alpha
Classifier: Intended Audience :: Developers
Classifier: License :: OSI Approved :: MIT License
Classifier: Programming Language :: Python :: 3
Classifier: Programming Language :: Python :: 3.9
Classifier: Programming Language :: Python :: 3.10
Classifier: Programming Language :: Python :: 3.11
Classifier: Programming Language :: Python :: 3.12
Classifier: Programming Language :: Python :: 3.13
Classifier: Programming Language :: Python :: 3.8
Requires-Dist: streamlit (>=1.0.0)
